pyrolab/__init__.py
pyrolab/api.py
pyrolab/cli.py
pyrolab/configure.py
pyrolab/manager.py
pyrolab/nameserver.py
pyrolab/pyrolabd.py
pyrolab/server.py
pyrolab/service.py
pyrolab/utils.py
pyrolab/data/wordlist.txt
pyrolab/drivers/VISAResourceExtensions.py
pyrolab/drivers/__init__.py
pyrolab/drivers/sample.py
pyrolab/drivers/arduino/__init__.py
pyrolab/drivers/arduino/arduino.py
pyrolab/drivers/cameras/__init__.py
pyrolab/drivers/cameras/amcam.py
pyrolab/drivers/cameras/sciTSI.py
pyrolab/drivers/cameras/thorcam.py
pyrolab/drivers/cameras/uc480.py
pyrolab/drivers/fpgas/__init__.py
pyrolab/drivers/fpgas/analogdiscovery.py
pyrolab/drivers/function_generators/__init__.py
pyrolab/drivers/function_generators/smcv100b.py
pyrolab/drivers/lasers/__init__.py
pyrolab/drivers/lasers/ppcl55x.py
pyrolab/drivers/lasers/sachertec.py
pyrolab/drivers/lasers/tsl550.py
pyrolab/drivers/motion/KMTS25E.py
pyrolab/drivers/motion/__init__.py
pyrolab/drivers/motion/max31x.py
pyrolab/drivers/motion/prm1z8.py
pyrolab/drivers/motion/z8xx.py
pyrolab/drivers/motion/kinesis/__init__.py
pyrolab/drivers/motion/kinesis/bpc303.py
pyrolab/drivers/motion/kinesis/kdc101.py
pyrolab/drivers/scopes/__init__.py
pyrolab/drivers/scopes/rohdeschwarz.py
pyrolab/drivers/smu/__init__.py
pyrolab/drivers/smu/keysight.py
pyrolab-0.4.0.dist-info/licenses/LICENSE
pyrolab-0.4.0.dist-info/licenses/NOTICE.txt
pyrolab-0.4.0.dist-info/METADATA
pyrolab-0.4.0.dist-info/WHEEL
pyrolab-0.4.0.dist-info/entry_points.txt
pyrolab-0.4.0.dist-info/top_level.txt
pyrolab-0.4.0.dist-info/RECORD
