Metadata-Version: 2.4
Name: pyrolab
Version: 0.4.0
Summary: A framework for using remote lab instruments as local resources built on Pyro5.
Author-email: Sequoia Ploeg <sequoiap4@gmail.com>, BYU CamachoLab <camacho@byu.edu>
Maintainer-email: Sequoia Ploeg <sequoiap4@gmail.com>, BYU CamachoLab <camacho@byu.edu>
License: GPL-3.0+
Project-URL: Homepage, https://pyrolab.readthedocs.io/en/latest/
Project-URL: Documentation, https://pyrolab.readthedocs.io/en/latest/
Project-URL: Source, https://github.com/BYUCamachoLab/pyrolab
Project-URL: Bug Reports, https://github.com/BYUCamachoLab/pyrolab/issues
Project-URL: Research Group, https://camacholab.byu.edu/
Keywords: PyroLab,Pyro5,Pyro,lab,instrument,remote,resources,framework,laboratory,instrumentation,hardware,science,remote,network,integration
Classifier: Development Status :: 4 - Beta
Classifier: Intended Audience :: Education
Classifier: Intended Audience :: Science/Research
Classifier: Intended Audience :: Developers
Classifier: Topic :: Scientific/Engineering
Classifier: License :: OSI Approved :: GNU General Public License v3 or later (GPLv3+)
Classifier: Programming Language :: Python :: 3
Classifier: Programming Language :: Python :: 3.9
Classifier: Programming Language :: Python :: 3.10
Classifier: Programming Language :: Python :: 3.11
Classifier: Programming Language :: Python :: 3.12
Classifier: Programming Language :: Python :: 3.13
Classifier: Programming Language :: Python :: 3 :: Only
Classifier: Operating System :: MacOS
Classifier: Operating System :: Microsoft :: Windows
Classifier: Operating System :: POSIX :: Linux
Classifier: Operating System :: OS Independent
Requires-Python: >=3.9
License-File: LICENSE
License-File: NOTICE.txt
Requires-Dist: numpy
Requires-Dist: scipy
Requires-Dist: Pyro5
Requires-Dist: pydantic<2.0.0,>=1.9.1
Requires-Dist: pyyaml
Requires-Dist: deprecation
Requires-Dist: typer
Requires-Dist: colorama
Requires-Dist: tabulate
Requires-Dist: requests
Requires-Dist: packaging>=23.0
Provides-Extra: tsl550
Requires-Dist: pyserial; extra == "tsl550"
Provides-Extra: ppcl55x
Requires-Dist: pyserial; extra == "ppcl55x"
Provides-Extra: rto
Requires-Dist: pyvisa; extra == "rto"
Requires-Dist: pyvisa-py; extra == "rto"
Provides-Extra: arduino
Requires-Dist: pyfirmata; extra == "arduino"
Provides-Extra: test
Requires-Dist: pytest; extra == "test"
Requires-Dist: coverage; extra == "test"
Provides-Extra: dev
Requires-Dist: notebook; extra == "dev"
Requires-Dist: pytest; extra == "dev"
Requires-Dist: mypy; extra == "dev"
Requires-Dist: coverage; extra == "dev"
Requires-Dist: flake8>=4.0.1; extra == "dev"
Requires-Dist: isort>=5.10.1; extra == "dev"
Requires-Dist: black>=22.1.0; extra == "dev"
Requires-Dist: autopep8>=1.6.0; extra == "dev"
Requires-Dist: twine>=4.0.0; extra == "dev"
Requires-Dist: build>=0.10.0; extra == "dev"
Requires-Dist: pre-commit; extra == "dev"
Requires-Dist: bump2version~=1.0.1; extra == "dev"
Provides-Extra: docs
Requires-Dist: jupyter-book==1.0.3; extra == "docs"
Requires-Dist: numpydoc==1.5.0; extra == "docs"
Dynamic: license-file
